odoo/addons/auth_saml/README.rst
odoo/addons/auth_saml/__init__.py
odoo/addons/auth_saml/__manifest__.py
odoo/addons/auth_saml/controllers/__init__.py
odoo/addons/auth_saml/controllers/main.py
odoo/addons/auth_saml/demo/auth_saml.xml
odoo/addons/auth_saml/i18n/auth_saml.pot
odoo/addons/auth_saml/i18n/fr.po
odoo/addons/auth_saml/models/__init__.py
odoo/addons/auth_saml/models/auth_saml.py
odoo/addons/auth_saml/models/res_users.py
odoo/addons/auth_saml/models/saml_token.py
odoo/addons/auth_saml/readme/CONFIGURE.rst
odoo/addons/auth_saml/readme/CONTRIBUTORS.rst
odoo/addons/auth_saml/readme/DESCRIPTION.rst
odoo/addons/auth_saml/readme/HISTORY.rst
odoo/addons/auth_saml/readme/INSTALL.rst
odoo/addons/auth_saml/readme/ROADMAP.rst
odoo/addons/auth_saml/readme/USAGE.rst
odoo/addons/auth_saml/security/ir.model.access.csv
odoo/addons/auth_saml/static/description/icon.png
odoo/addons/auth_saml/static/description/index.html
odoo/addons/auth_saml/views/auth_saml.xml
odoo/addons/auth_saml/views/base_settings.xml
odoo/addons/auth_saml/views/res_users.xml
odoo/addons/auth_saml/wizards/__init__.py
odoo/addons/auth_saml/wizards/res_config_settings.py
odoo12_addon_auth_saml-12.0.1.0.1.dist-info/METADATA
odoo12_addon_auth_saml-12.0.1.0.1.dist-info/WHEEL
odoo12_addon_auth_saml-12.0.1.0.1.dist-info/top_level.txt
odoo12_addon_auth_saml-12.0.1.0.1.dist-info/RECORD
