Metadata-Version: 2.1
Name: odoo12-addon-auth-saml
Version: 12.0.1.0.1
Summary: Saml2 Authentication
Home-page: https://github.com/OCA/server-auth
Author: XCG Consulting, Odoo Community Association (OCA)
Author-email: support@odoo-community.org
License: AGPL-3
Platform: UNKNOWN
Classifier: Programming Language :: Python
Classifier: Framework :: Odoo
Classifier: License :: OSI Approved :: GNU Affero General Public License v3
Requires-Python: >=3.5
Requires-Dist: lasso
Requires-Dist: odoo (<12.1dev,>=12.0a)
